benzene_ring/__init__.py
benzene_ring/statistics.py
benzene_ring-1.2.0.dist-info/LICENSE
benzene_ring-1.2.0.dist-info/METADATA
benzene_ring-1.2.0.dist-info/WHEEL
benzene_ring-1.2.0.dist-info/top_level.txt
benzene_ring-1.2.0.dist-info/RECORD
